{
  "minecraft:recipes/combat/wooden_sword": {
    "criteria": {
      "has_stick": "2020-11-27 21:53:31 -0500"
    },
    "done": true
  },
  "minecraft:recipes/decorations/item_frame": {
    "criteria": {
      "has_leather": "2020-11-27 21:53:04 -0500"
    },
    "done": true
  },
  "minecraft:recipes/building_blocks/oak_planks": {
    "criteria": {
      "has_logs": "2020-11-27 21:59:09 -0500"
    },
    "done": true
  },
  "minecraft:recipes/combat/leather_chestplate": {
    "criteria": {
      "has_leather": "2020-11-27 21:53:04 -0500"
    },
    "done": true
  },
  "minecraft:recipes/tools/wooden_axe": {
    "criteria": {
      "has_stick": "2020-11-27 21:53:31 -0500"
    },
    "done": true
  },
  "minecraft:recipes/transportation/dark_oak_boat": {
    "criteria": {
      "in_water": "2020-11-27 21:28:32 -0500"
    },
    "done": true
  },
  "minecraft:recipes/misc/conduit": {
    "criteria": {
      "has_nautilus_shell": "2020-11-27 21:38:57 -0500"
    },
    "done": true
  },
  "minecraft:adventure/kill_a_mob": {
    "criteria": {
      "minecraft:drowned": "2020-11-27 21:32:50 -0500"
    },
    "done": true
  },
  "minecraft:adventure/kill_all_mobs": {
    "criteria": {
      "minecraft:zombie": "2020-11-27 22:22:01 -0500",
      "minecraft:drowned": "2020-11-27 21:32:50 -0500"
    },
    "done": false
  },
  "minecraft:recipes/food/cake": {
    "criteria": {
      "has_egg": "2020-11-27 21:49:36 -0500"
    },
    "done": true
  },
  "minecraft:recipes/misc/paper": {
    "criteria": {
      "has_reeds": "2020-11-27 21:36:55 -0500"
    },
    "done": true
  },
  "minecraft:recipes/misc/sugar_from_sugar_cane": {
    "criteria": {
      "has_reeds": "2020-11-27 21:36:55 -0500"
    },
    "done": true
  },
  "minecraft:recipes/building_blocks/birch_wood": {
    "criteria": {
      "has_log": "2020-11-27 22:05:24 -0500"
    },
    "done": true
  },
  "minecraft:husbandry/balanced_diet": {
    "criteria": {
      "sweet_berries": "2020-11-27 22:01:20 -0500"
    },
    "done": false
  },
  "minecraft:recipes/tools/wooden_hoe": {
    "criteria": {
      "has_stick": "2020-11-27 21:53:31 -0500"
    },
    "done": true
  },
  "minecraft:recipes/food/cooked_beef_from_smoking": {
    "criteria": {
      "has_beef": "2020-11-27 21:53:04 -0500"
    },
    "done": true
  },
  "minecraft:recipes/misc/light_gray_dye_from_azure_bluet": {
    "criteria": {
      "has_red_flower": "2020-11-27 22:04:26 -0500"
    },
    "done": true
  },
  "minecraft:recipes/combat/leather_helmet": {
    "criteria": {
      "has_leather": "2020-11-27 21:53:04 -0500"
    },
    "done": true
  },
  "minecraft:recipes/food/cooked_beef": {
    "criteria": {
      "has_beef": "2020-11-27 21:53:04 -0500"
    },
    "done": true
  },
  "minecraft:adventure/adventuring_time": {
    "criteria": {
      "minecraft:cold_ocean": "2020-11-27 21:41:50 -0500",
      "minecraft:forest": "2020-11-27 21:37:01 -0500",
      "minecraft:taiga": "2020-11-27 21:46:27 -0500",
      "minecraft:deep_cold_ocean": "2020-11-27 21:36:36 -0500",
      "minecraft:taiga_hills": "2020-11-27 21:46:45 -0500",
      "minecraft:beach": "2020-11-27 21:27:05 -0500",
      "minecraft:river": "2020-11-27 21:36:37 -0500",
      "minecraft:wooded_hills": "2020-11-27 22:03:23 -0500",
      "minecraft:plains": "2020-11-27 22:02:34 -0500"
    },
    "done": false
  },
  "minecraft:recipes/building_blocks/birch_planks": {
    "criteria": {
      "has_logs": "2020-11-27 22:05:24 -0500"
    },
    "done": true
  },
  "minecraft:recipes/decorations/campfire": {
    "criteria": {
      "has_stick": "2020-11-27 21:53:31 -0500"
    },
    "done": true
  },
  "minecraft:recipes/misc/charcoal": {
    "criteria": {
      "has_log": "2020-11-27 21:59:09 -0500"
    },
    "done": true
  },
  "minecraft:recipes/tools/wooden_pickaxe": {
    "criteria": {
      "has_stick": "2020-11-27 21:53:31 -0500"
    },
    "done": true
  },
  "minecraft:recipes/decorations/ladder": {
    "criteria": {
      "has_stick": "2020-11-27 21:53:31 -0500"
    },
    "done": true
  },
  "minecraft:husbandry/root": {
    "criteria": {
      "consumed_item": "2020-11-27 22:01:20 -0500"
    },
    "done": true
  },
  "minecraft:recipes/food/cooked_beef_from_campfire_cooking": {
    "criteria": {
      "has_beef": "2020-11-27 21:53:04 -0500"
    },
    "done": true
  },
  "minecraft:recipes/transportation/birch_boat": {
    "criteria": {
      "in_water": "2020-11-27 21:28:32 -0500"
    },
    "done": true
  },
  "minecraft:recipes/decorations/chest": {
    "criteria": {
      "has_lots_of_items": "2020-11-27 21:54:40 -0500"
    },
    "done": true
  },
  "minecraft:recipes/building_blocks/oak_wood": {
    "criteria": {
      "has_log": "2020-11-27 21:59:09 -0500"
    },
    "done": true
  },
  "minecraft:recipes/tools/wooden_shovel": {
    "criteria": {
      "has_stick": "2020-11-27 21:53:31 -0500"
    },
    "done": true
  },
  "minecraft:recipes/misc/red_dye_from_poppy": {
    "criteria": {
      "has_red_flower": "2020-11-27 22:02:12 -0500"
    },
    "done": true
  },
  "minecraft:recipes/transportation/acacia_boat": {
    "criteria": {
      "in_water": "2020-11-27 21:28:32 -0500"
    },
    "done": true
  },
  "minecraft:recipes/misc/light_gray_dye_from_oxeye_daisy": {
    "criteria": {
      "has_red_flower": "2020-11-27 22:17:16 -0500"
    },
    "done": true
  },
  "minecraft:recipes/transportation/oak_boat": {
    "criteria": {
      "in_water": "2020-11-27 21:28:32 -0500"
    },
    "done": true
  },
  "minecraft:recipes/decorations/soul_campfire": {
    "criteria": {
      "has_stick": "2020-11-27 21:53:31 -0500"
    },
    "done": true
  },
  "minecraft:recipes/combat/crossbow": {
    "criteria": {
      "has_stick": "2020-11-27 21:53:31 -0500"
    },
    "done": true
  },
  "minecraft:adventure/root": {
    "criteria": {
      "killed_something": "2020-11-27 21:32:50 -0500"
    },
    "done": true
  },
  "minecraft:recipes/combat/leather_boots": {
    "criteria": {
      "has_leather": "2020-11-27 21:53:04 -0500"
    },
    "done": true
  },
  "minecraft:recipes/transportation/jungle_boat": {
    "criteria": {
      "in_water": "2020-11-27 21:28:32 -0500"
    },
    "done": true
  },
  "minecraft:recipes/misc/yellow_dye_from_dandelion": {
    "criteria": {
      "has_yellow_flower": "2020-11-27 21:54:58 -0500"
    },
    "done": true
  },
  "minecraft:recipes/transportation/spruce_boat": {
    "criteria": {
      "in_water": "2020-11-27 21:28:32 -0500"
    },
    "done": true
  },
  "minecraft:recipes/misc/leather_horse_armor": {
    "criteria": {
      "has_leather": "2020-11-27 21:53:04 -0500"
    },
    "done": true
  },
  "minecraft:recipes/misc/flower_banner_pattern": {
    "criteria": {
      "has_oxeye_daisy": "2020-11-27 22:17:16 -0500"
    },
    "done": true
  },
  "minecraft:recipes/combat/leather_leggings": {
    "criteria": {
      "has_leather": "2020-11-27 21:53:04 -0500"
    },
    "done": true
  },
  "DataVersion": 2584
}