{
  "minecraft:recipes/combat/wooden_sword": {
    "criteria": {
      "has_stick": "2020-11-29 22:46:31 +0000"
    },
    "done": true
  },
  "minecraft:recipes/tools/stone_shovel": {
    "criteria": {
      "has_cobblestone": "2020-11-29 22:46:35 +0000"
    },
    "done": true
  },
  "minecraft:recipes/tools/wooden_axe": {
    "criteria": {
      "has_stick": "2020-11-29 22:46:31 +0000"
    },
    "done": true
  },
  "minecraft:recipes/tools/stone_hoe": {
    "criteria": {
      "has_cobblestone": "2020-11-29 22:46:35 +0000"
    },
    "done": true
  },
  "minecraft:recipes/transportation/dark_oak_boat": {
    "criteria": {
      "in_water": "2020-11-29 22:45:39 +0000"
    },
    "done": true
  },
  "minecraft:recipes/redstone/lever": {
    "criteria": {
      "has_cobblestone": "2020-11-29 22:46:35 +0000"
    },
    "done": true
  },
  "minecraft:recipes/building_blocks/cobblestone_stairs_from_cobblestone_stonecutting": {
    "criteria": {
      "has_cobblestone": "2020-11-29 22:46:35 +0000"
    },
    "done": true
  },
  "minecraft:recipes/tools/wooden_hoe": {
    "criteria": {
      "has_stick": "2020-11-29 22:46:31 +0000"
    },
    "done": true
  },
  "minecraft:story/mine_stone": {
    "criteria": {
      "get_stone": "2020-11-29 22:46:35 +0000"
    },
    "done": true
  },
  "minecraft:recipes/building_blocks/stone": {
    "criteria": {
      "has_cobblestone": "2020-11-29 22:46:35 +0000"
    },
    "done": true
  },
  "minecraft:recipes/building_blocks/cobblestone_slab": {
    "criteria": {
      "has_cobblestone": "2020-11-29 22:46:35 +0000"
    },
    "done": true
  },
  "minecraft:recipes/decorations/furnace": {
    "criteria": {
      "has_cobblestone": "2020-11-29 22:46:35 +0000"
    },
    "done": true
  },
  "minecraft:adventure/adventuring_time": {
    "criteria": {
      "minecraft:beach": "2020-11-29 22:45:38 +0000",
      "minecraft:lukewarm_ocean": "2020-11-29 22:46:05 +0000",
      "minecraft:plains": "2020-11-29 22:45:10 +0000"
    },
    "done": false
  },
  "minecraft:recipes/building_blocks/cobblestone_stairs": {
    "criteria": {
      "has_cobblestone": "2020-11-29 22:46:35 +0000"
    },
    "done": true
  },
  "minecraft:recipes/decorations/campfire": {
    "criteria": {
      "has_stick": "2020-11-29 22:46:31 +0000"
    },
    "done": true
  },
  "minecraft:recipes/tools/wooden_pickaxe": {
    "criteria": {
      "has_stick": "2020-11-29 22:46:31 +0000"
    },
    "done": true
  },
  "minecraft:recipes/building_blocks/cobblestone_slab_from_cobblestone_stonecutting": {
    "criteria": {
      "has_cobblestone": "2020-11-29 22:46:35 +0000"
    },
    "done": true
  },
  "minecraft:recipes/decorations/ladder": {
    "criteria": {
      "has_stick": "2020-11-29 22:46:31 +0000"
    },
    "done": true
  },
  "minecraft:recipes/transportation/birch_boat": {
    "criteria": {
      "in_water": "2020-11-29 22:45:39 +0000"
    },
    "done": true
  },
  "minecraft:recipes/combat/stone_sword": {
    "criteria": {
      "has_cobblestone": "2020-11-29 22:46:35 +0000"
    },
    "done": true
  },
  "minecraft:recipes/decorations/cobblestone_wall": {
    "criteria": {
      "has_cobblestone": "2020-11-29 22:46:35 +0000"
    },
    "done": true
  },
  "minecraft:recipes/tools/wooden_shovel": {
    "criteria": {
      "has_stick": "2020-11-29 22:46:31 +0000"
    },
    "done": true
  },
  "minecraft:recipes/transportation/acacia_boat": {
    "criteria": {
      "in_water": "2020-11-29 22:45:39 +0000"
    },
    "done": true
  },
  "minecraft:recipes/tools/stone_pickaxe": {
    "criteria": {
      "has_cobblestone": "2020-11-29 22:46:35 +0000"
    },
    "done": true
  },
  "minecraft:recipes/decorations/soul_campfire": {
    "criteria": {
      "has_stick": "2020-11-29 22:46:31 +0000"
    },
    "done": true
  },
  "minecraft:recipes/combat/crossbow": {
    "criteria": {
      "has_stick": "2020-11-29 22:46:31 +0000"
    },
    "done": true
  },
  "minecraft:recipes/transportation/oak_boat": {
    "criteria": {
      "in_water": "2020-11-29 22:45:39 +0000"
    },
    "done": true
  },
  "minecraft:recipes/tools/stone_axe": {
    "criteria": {
      "has_cobblestone": "2020-11-29 22:46:35 +0000"
    },
    "done": true
  },
  "minecraft:recipes/transportation/jungle_boat": {
    "criteria": {
      "in_water": "2020-11-29 22:45:39 +0000"
    },
    "done": true
  },
  "minecraft:recipes/decorations/cobblestone_wall_from_cobblestone_stonecutting": {
    "criteria": {
      "has_cobblestone": "2020-11-29 22:46:35 +0000"
    },
    "done": true
  },
  "minecraft:recipes/transportation/spruce_boat": {
    "criteria": {
      "in_water": "2020-11-29 22:45:39 +0000"
    },
    "done": true
  },
  "DataVersion": 2584
}