{"stats":{"minecraft:killed":{"minecraft:witch":1,"minecraft:spider":55,"minecraft:cod":5,"minecraft:skeleton":36,"minecraft:chicken":59,"minecraft:silverfish":3,"minecraft:cat":1,"minecraft:piglin":1,"minecraft:pig":9,"minecraft:zombie_villager":4,"minecraft:creeper":8,"minecraft:pillager":4,"minecraft:zombie":185,"minecraft:blaze":1,"minecraft:cow":19,"minecraft:slime":1,"minecraft:phantom":15,"minecraft:drowned":24,"minecraft:husk":4,"minecraft:bat":1,"minecraft:enderman":8},"minecraft:used":{"minecraft:peony":98,"minecraft:iron_shovel":7090,"minecraft:poppy":11,"minecraft:oak_sign":22,"minecraft:chest":21,"minecraft:shield":293,"minecraft:stone":1030,"minecraft:iron_sword":1613,"minecraft:nether_wart":1,"minecraft:spruce_leaves":945,"minecraft:lily_of_the_valley":20,"minecraft:carrot":415,"minecraft:snowball":5,"minecraft:azure_bluet":20,"minecraft:stripped_spruce_log":1,"minecraft:spruce_boat":6,"minecraft:lava_bucket":33,"minecraft:coal_ore":6,"minecraft:grass_block":253,"minecraft:stone_brick_stairs":60,"minecraft:stone_bricks":615,"minecraft:item_frame":10,"minecraft:golden_sword":16,"minecraft:bow":9,"minecraft:sweet_berries":718,"minecraft:oak_sapling":1,"minecraft:furnace":9,"minecraft:cooked_cod":8,"minecraft:gold_block":14,"minecraft:egg":1616,"minecraft:potato":331,"minecraft:mossy_stone_bricks":209,"minecraft:diorite":37,"minecraft:chorus_fruit":32,"minecraft:stone_pickaxe":765,"minecraft:oak_planks":110,"minecraft:ender_pearl":2,"minecraft:orange_tulip":10,"minecraft:wooden_pickaxe":39,"minecraft:sandstone":95,"minecraft:redstone_block":1,"minecraft:diamond_axe":39,"minecraft:sugar_cane":25,"minecraft:oak_leaves":677,"minecraft:sand":186,"minecraft:crossbow":71,"minecraft:shears":2150,"minecraft:redstone_torch":4,"minecraft:bread":39,"minecraft:melon_slice":36,"minecraft:lilac":11,"minecraft:diamond_sword":1,"minecraft:wooden_sword":53,"minecraft:poisonous_potato":2,"minecraft:andesite":27,"minecraft:oak_boat":65,"minecraft:oak_fence":93,"minecraft:trident":32,"minecraft:rose_bush":209,"minecraft:stone_sword":340,"minecraft:stone_shovel":1229,"minecraft:spruce_planks":51,"minecraft:cooked_chicken":211,"minecraft:netherrack":2,"minecraft:torch":562,"minecraft:dragon_egg":1,"minecraft:dirt":5799,"minecraft:stone_stairs":44,"minecraft:granite":652,"minecraft:spruce_fence":2,"minecraft:oak_fence_gate":1,"minecraft:mossy_cobblestone_stairs":24,"minecraft:wooden_axe":25,"minecraft:red_tulip":6,"minecraft:oak_stairs":16,"minecraft:light_gray_wool":5,"minecraft:emerald_block":1,"minecraft:beef":1,"minecraft:minecart":1,"minecraft:cooked_beef":28,"minecraft:acacia_planks":2,"minecraft:brown_bed":1,"minecraft:wheat_seeds":208,"minecraft:cooked_mutton":4,"minecraft:water_bucket":184,"minecraft:baked_potato":190,"minecraft:cartography_table":4,"minecraft:birch_boat":4,"minecraft:cracked_stone_bricks":6,"minecraft:mossy_cobblestone":231,"minecraft:vine":485,"minecraft:crafting_table":22,"minecraft:oak_slab":48,"minecraft:campfire":1,"minecraft:white_bed":12,"minecraft:spruce_log":9,"minecraft:oak_log":17,"minecraft:apple":1,"minecraft:diamond_pickaxe":5542,"minecraft:cornflower":76,"minecraft:oxeye_daisy":13,"minecraft:diamond_shovel":4699,"minecraft:acacia_sign":1,"minecraft:chicken":1,"minecraft:iron_pickaxe":7708,"minecraft:stone_slab":26,"minecraft:fishing_rod":64,"minecraft:cobblestone":1760,"minecraft:porkchop":5,"minecraft:cooked_porkchop":40,"minecraft:bucket":216,"minecraft:yellow_bed":1,"minecraft:dandelion":2},"minecraft:broken":{"minecraft:golden_helmet":1,"minecraft:iron_shovel":28,"minecraft:shears":8,"minecraft:leather_leggings":2,"minecraft:iron_boots":2,"minecraft:iron_chestplate":2,"minecraft:iron_leggings":2,"minecraft:stone_pickaxe":5,"minecraft:diamond_shovel":3,"minecraft:golden_sword":1,"minecraft:iron_sword":3,"minecraft:fishing_rod":1,"minecraft:stone_shovel":9,"minecraft:stone_sword":3,"minecraft:wooden_pickaxe":1,"minecraft:shield":2,"minecraft:iron_pickaxe":29,"minecraft:iron_helmet":3},"minecraft:crafted":{"minecraft:oak_planks":410,"minecraft:smooth_stone":1,"minecraft:oak_sign":3,"minecraft:birch_boat":4,"minecraft:cooked_chicken":55,"minecraft:stone":430,"minecraft:diamond_shovel":3,"minecraft:iron_boots":3,"minecraft:chest":10,"minecraft:stone_bricks":636,"minecraft:oak_fence":50,"minecraft:oak_slab":48,"minecraft:cooked_porkchop":37,"minecraft:map":11,"minecraft:crafting_table":9,"minecraft:spruce_planks":96,"minecraft:baked_potato":307,"minecraft:wooden_pickaxe":2,"minecraft:iron_helmet":3,"minecraft:mossy_cobblestone":168,"minecraft:brown_bed":1,"minecraft:birch_planks":26,"minecraft:stone_brick_stairs":36,"minecraft:charcoal":18,"minecraft:paper":225,"minecraft:iron_chestplate":3,"minecraft:diamond_pickaxe":2,"minecraft:shield":5,"minecraft:iron_ingot":162,"minecraft:stick":230,"minecraft:stone_slab":48,"minecraft:compass":13,"minecraft:iron_pickaxe":32,"minecraft:stone_sword":3,"minecraft:shears":10,"minecraft:wooden_sword":1,"minecraft:stone_shovel":10,"minecraft:mossy_stone_bricks":86,"minecraft:furnace":3,"minecraft:mossy_cobblestone_stairs":16,"minecraft:oak_trapdoor":2,"minecraft:stone_stairs":36,"minecraft:stone_pickaxe":7,"minecraft:filled_map":9,"minecraft:spruce_boat":2,"minecraft:cooked_beef":34,"minecraft:iron_sword":5,"minecraft:bucket":3,"minecraft:air":0,"minecraft:oak_fence_gate":1,"minecraft:oak_boat":15,"minecraft:wooden_axe":1,"minecraft:oak_stairs":8,"minecraft:iron_shovel":30,"minecraft:iron_leggings":3,"minecraft:white_bed":4,"minecraft:torch":116},"minecraft:dropped":{"minecraft:iron_sword":12,"minecraft:diamond_axe":1,"minecraft:lapis_lazuli":58,"minecraft:cooked_beef":34,"minecraft:oak_log":18,"minecraft:baked_potato":136,"minecraft:chorus_fruit":5,"minecraft:diamond":29,"minecraft:dark_oak_sapling":8,"minecraft:cooked_porkchop":5,"minecraft:crossbow":2,"minecraft:lantern":1,"minecraft:leather":2,"minecraft:red_mushroom":1,"minecraft:cod":1,"minecraft:flint":6,"minecraft:spruce_leaves":319,"minecraft:dirt":371,"minecraft:grass":1,"minecraft:cornflower":5,"minecraft:mutton":22,"minecraft:sunflower":3,"minecraft:gold_nugget":3,"minecraft:wooden_sword":1,"minecraft:bone_meal":1,"minecraft:phantom_membrane":3,"minecraft:sand":143,"minecraft:iron_pickaxe":6,"minecraft:fishing_rod":2,"minecraft:bone":16,"minecraft:gravel":19,"minecraft:emerald_block":1,"minecraft:sugar_cane":12,"minecraft:iron_nugget":8,"minecraft:cooked_chicken":24,"minecraft:wheat":71,"minecraft:birch_sapling":7,"minecraft:obsidian":11,"minecraft:pink_dye":1,"minecraft:rotten_flesh":253,"minecraft:oak_planks":1,"minecraft:diamond_shovel":2,"minecraft:stone_stairs":6,"minecraft:azure_bluet":3,"minecraft:carrot":154,"minecraft:salmon":14,"minecraft:poppy":13,"minecraft:oak_fence_gate":4,"minecraft:trident":2,"minecraft:gunpowder":2,"minecraft:charcoal":2,"minecraft:chest":2,"minecraft:leather_leggings":2,"minecraft:iron_ore":2,"minecraft:arrow":49,"minecraft:glass":36,"minecraft:quartz":6,"minecraft:stone_brick_stairs":2,"minecraft:oak_leaves":39,"minecraft:netherrack":9,"minecraft:egg":75,"minecraft:bread":1,"minecraft:iron_ingot":10,"minecraft:water_bucket":1,"minecraft:vine":63,"minecraft:wheat_seeds":138,"minecraft:clock":1,"minecraft:tnt":6,"minecraft:feather":55,"minecraft:lead":1,"minecraft:poisonous_potato":10,"minecraft:book":11,"minecraft:cobblestone":425,"minecraft:oak_fence":3,"minecraft:iron_helmet":2,"minecraft:apple":4,"minecraft:granite":12,"minecraft:coal":88,"minecraft:stick":36,"minecraft:oxeye_daisy":7,"minecraft:diorite":31,"minecraft:torch":72,"minecraft:rose_bush":7,"minecraft:iron_leggings":3,"minecraft:iron_axe":1,"minecraft:smooth_stone":1,"minecraft:string":61,"minecraft:iron_shovel":6,"minecraft:paper":262,"minecraft:lily_pad":33,"minecraft:bucket":2,"minecraft:spruce_sapling":26,"minecraft:dandelion":14,"minecraft:kelp":69,"minecraft:sweet_berries":351,"minecraft:stone_sword":1,"minecraft:bowl":4,"minecraft:stone_shovel":2,"minecraft:chicken":3,"minecraft:iron_boots":3,"minecraft:stone_slab":4,"minecraft:nether_bricks":8,"minecraft:spruce_fence":1,"minecraft:oak_sign":1,"minecraft:shears":7,"minecraft:stone":99,"minecraft:diamond_sword":2,"minecraft:filled_map":31,"minecraft:potato":21,"minecraft:shield":2,"minecraft:peony":1,"minecraft:spruce_planks":134,"minecraft:diamond_pickaxe":5,"minecraft:iron_chestplate":2,"minecraft:dragon_egg":1,"minecraft:andesite":3,"minecraft:mossy_stone_bricks":2,"minecraft:oak_boat":7,"minecraft:oak_sapling":37,"minecraft:stone_bricks":4,"minecraft:bamboo":3,"minecraft:spider_eye":25,"minecraft:sandstone":57,"minecraft:spruce_log":50,"minecraft:birch_boat":4,"minecraft:bow":3,"minecraft:stone_pickaxe":3,"minecraft:wooden_pickaxe":2},"minecraft:killed_by":{"minecraft:zombie_villager":1,"minecraft:creeper":9,"minecraft:drowned":2,"minecraft:witch":4,"minecraft:zombie":29,"minecraft:player":23,"minecraft:spider":7,"minecraft:enderman":13,"minecraft:ender_dragon":1,"minecraft:skeleton":21,"minecraft:phantom":4},"minecraft:mined":{"minecraft:dark_oak_planks":5,"minecraft:spruce_planks":18,"minecraft:white_bed":8,"minecraft:jungle_slab":1,"minecraft:light_blue_carpet":1,"minecraft:granite":914,"minecraft:grass_block":6133,"minecraft:coal_block":3,"minecraft:oak_wall_sign":7,"minecraft:oxeye_daisy":82,"minecraft:nether_wart":1,"minecraft:tall_seagrass":6,"minecraft:magma_block":1,"minecraft:mossy_cobblestone_stairs":11,"minecraft:dark_oak_trapdoor":1,"minecraft:iron_ore":101,"minecraft:fire":8,"minecraft:pumpkin":3,"minecraft:anvil":1,"minecraft:azure_bluet":101,"minecraft:dark_oak_stairs":2,"minecraft:brown_bed":1,"minecraft:red_tulip":31,"minecraft:oak_sign":1,"minecraft:oak_stairs":8,"minecraft:pink_tulip":22,"minecraft:spruce_slab":3,"minecraft:cut_sandstone":1,"minecraft:brown_mushroom":25,"minecraft:kelp_plant":54,"minecraft:orange_terracotta":5,"minecraft:torch":87,"minecraft:jungle_stairs":1,"minecraft:poppy":127,"minecraft:chest":11,"minecraft:dead_bush":33,"minecraft:nether_quartz_ore":169,"minecraft:glass":4,"minecraft:cobblestone":1250,"minecraft:sugar_cane":322,"minecraft:oak_planks":25,"minecraft:wall_torch":120,"minecraft:spruce_sign":3,"minecraft:seagrass":12,"minecraft:stone_stairs":14,"minecraft:birch_log":5,"minecraft:wheat":167,"minecraft:lilac":71,"minecraft:light_gray_wool":4,"minecraft:orange_tulip":141,"minecraft:stone_brick_stairs":22,"minecraft:smooth_stone_slab":1,"minecraft:grass":2156,"minecraft:oak_log":123,"minecraft:oak_fence_gate":1,"minecraft:sand":799,"minecraft:dirt":5097,"minecraft:netherrack":381,"minecraft:oak_leaves":658,"minecraft:emerald_block":1,"minecraft:mossy_cobblestone":182,"minecraft:dark_oak_log":3,"minecraft:end_stone":48,"minecraft:nether_bricks":48,"minecraft:ladder":1,"minecraft:allium":13,"minecraft:spruce_fence":1,"minecraft:jungle_planks":3,"minecraft:spruce_leaves":1020,"minecraft:kelp":31,"minecraft:cartography_table":4,"minecraft:sandstone":324,"minecraft:large_fern":32,"minecraft:hay_block":29,"minecraft:redstone_ore":20,"minecraft:furnace":6,"minecraft:carrots":142,"minecraft:andesite":517,"minecraft:stripped_spruce_log":1,"minecraft:peony":116,"minecraft:gold_block":13,"minecraft:nether_brick_fence":1,"minecraft:potatoes":155,"minecraft:vine":784,"minecraft:lantern":1,"minecraft:packed_ice":112,"minecraft:chorus_plant":6,"minecraft:white_tulip":35,"minecraft:stone":8336,"minecraft:oak_slab":8,"minecraft:infested_stone_bricks":4,"minecraft:lily_of_the_valley":81,"minecraft:dandelion":146,"minecraft:oak_fence":33,"minecraft:crafting_table":14,"minecraft:cornflower":222,"minecraft:rose_bush":222,"minecraft:campfire":1,"minecraft:stone_slab":25,"minecraft:tall_grass":198,"minecraft:diorite":444,"minecraft:spruce_stairs":1,"minecraft:birch_planks":23,"minecraft:redstone_torch":1,"minecraft:sweet_berry_bush":57,"minecraft:spruce_log":63,"minecraft:birch_leaves":18,"minecraft:yellow_bed":1,"minecraft:grass_path":503,"minecraft:coal_ore":211,"minecraft:sunflower":72,"minecraft:gravel":170,"minecraft:cobweb":19,"minecraft:cracked_stone_bricks":8,"minecraft:spruce_fence_gate":1,"minecraft:stone_bricks":91,"minecraft:mossy_stone_bricks":144,"minecraft:acacia_wall_sign":1,"minecraft:fern":76},"minecraft:custom":{"minecraft:animals_bred":246,"minecraft:interact_with_crafting_table":342,"minecraft:open_barrel":5,"minecraft:bell_ring":5,"minecraft:leave_game":110,"minecraft:time_since_death":57995,"minecraft:sprint_one_cm":14983015,"minecraft:damage_blocked_by_shield":12320,"minecraft:drop":1131,"minecraft:talked_to_villager":6,"minecraft:deaths":136,"minecraft:jump":55348,"minecraft:interact_with_brewingstand":1,"minecraft:walk_on_water_one_cm":1161200,"minecraft:enchant_item":3,"minecraft:interact_with_furnace":154,"minecraft:interact_with_cartography_table":44,"minecraft:play_one_minute":6779560,"minecraft:sleep_in_bed":86,"minecraft:open_enderchest":9,"minecraft:damage_dealt":87387,"minecraft:player_kills":4,"minecraft:crouch_one_cm":165231,"minecraft:interact_with_smoker":14,"minecraft:horse_one_cm":4970176,"minecraft:interact_with_anvil":5,"minecraft:mob_kills":456,"minecraft:climb_one_cm":181482,"minecraft:walk_one_cm":31141759,"minecraft:sneak_time":76770,"minecraft:walk_under_water_one_cm":1114796,"minecraft:boat_one_cm":15184765,"minecraft:interact_with_blast_furnace":17,"minecraft:raid_trigger":1,"minecraft:interact_with_grindstone":5,"minecraft:interact_with_stonecutter":1,"minecraft:time_since_rest":58015,"minecraft:damage_taken":86462,"minecraft:trigger_trapped_chest":21,"minecraft:minecart_one_cm":44089,"minecraft:swim_one_cm":594144,"minecraft:fly_one_cm":5341909,"minecraft:open_chest":1306,"minecraft:fish_caught":4,"minecraft:fall_one_cm":830449},"minecraft:picked_up":{"minecraft:seagrass":11,"minecraft:iron_chestplate":23,"minecraft:wheat":217,"minecraft:redstone_block":63,"minecraft:nether_brick_fence":3,"minecraft:suspicious_stew":1,"minecraft:lead":7,"minecraft:stone_slab":76,"minecraft:diamond_sword":3,"minecraft:oak_stairs":9,"minecraft:stone_brick_stairs":28,"minecraft:golden_sword":3,"minecraft:string":112,"minecraft:dark_oak_trapdoor":1,"minecraft:cooked_salmon":7,"minecraft:smooth_stone_slab":3,"minecraft:iron_leggings":24,"minecraft:pufferfish":2,"minecraft:experience_bottle":3,"minecraft:oak_sign":33,"minecraft:gold_nugget":129,"minecraft:bucket":5,"minecraft:spruce_planks":295,"minecraft:acacia_sign":1,"minecraft:light_weighted_pressure_plate":1,"minecraft:white_tulip":35,"minecraft:redstone_torch":5,"minecraft:rose_bush":320,"minecraft:iron_pickaxe":27,"minecraft:coal_block":3,"minecraft:melon_slice":45,"minecraft:iron_boots":21,"minecraft:furnace":10,"minecraft:golden_helmet":1,"minecraft:stick":245,"minecraft:oak_fence":56,"minecraft:torch":1176,"minecraft:spruce_stairs":1,"minecraft:porkchop":20,"minecraft:diorite":554,"minecraft:vine":904,"minecraft:stone_sword":11,"minecraft:cactus":13,"minecraft:light_gray_bed":1,"minecraft:rotten_flesh":511,"minecraft:tropical_fish":11,"minecraft:red_tulip":18,"minecraft:iron_block":1,"minecraft:carved_pumpkin":2,"minecraft:blaze_rod":1,"minecraft:obsidian":12,"minecraft:cod":16,"minecraft:snowball":5,"minecraft:cobblestone":8020,"minecraft:birch_log":7,"minecraft:lilac":119,"minecraft:feather":222,"minecraft:cooked_beef":109,"minecraft:magma_cream":1,"minecraft:iron_door":8,"minecraft:water_bucket":4,"minecraft:andesite":597,"minecraft:brown_wool":5,"minecraft:potato":621,"minecraft:flint":34,"minecraft:map":7,"minecraft:lapis_lazuli":96,"minecraft:dirt":9687,"minecraft:lantern":1,"minecraft:glass":36,"minecraft:bone":132,"minecraft:acacia_planks":3,"minecraft:bow":13,"minecraft:orange_tulip":183,"minecraft:wheat_seeds":1180,"minecraft:mossy_stone_bricks":155,"minecraft:glowstone_dust":1,"minecraft:bamboo":7,"minecraft:oak_planks":258,"minecraft:cooked_porkchop":23,"minecraft:oak_pressure_plate":1,"minecraft:poisonous_potato":12,"minecraft:jungle_planks":4,"minecraft:sand":1041,"minecraft:stripped_spruce_log":6,"minecraft:ink_sac":2,"minecraft:grass_block":270,"minecraft:lily_of_the_valley":191,"minecraft:chiseled_sandstone":1,"minecraft:jungle_slab":1,"minecraft:dark_oak_log":86,"minecraft:mossy_cobblestone":353,"minecraft:iron_hoe":2,"minecraft:spruce_fence_gate":1,"minecraft:sugar":50,"minecraft:diamond":79,"minecraft:spruce_boat":6,"minecraft:crossbow":10,"minecraft:granite":1158,"minecraft:grass":121,"minecraft:bone_meal":1,"minecraft:spruce_sign":3,"minecraft:bread":81,"minecraft:emerald":33,"minecraft:oak_sapling":105,"minecraft:chorus_fruit":84,"minecraft:netherrack":257,"minecraft:oak_leaves":795,"minecraft:diamond_pickaxe":14,"minecraft:fishing_rod":11,"minecraft:spruce_leaves":1406,"minecraft:charcoal":2,"minecraft:coarse_dirt":10,"minecraft:crafting_table":19,"minecraft:allium":10,"minecraft:azure_bluet":167,"minecraft:chicken":157,"minecraft:nether_wart":5,"minecraft:leather_leggings":5,"minecraft:brown_mushroom":27,"minecraft:wooden_pickaxe":1,"minecraft:gold_block":15,"minecraft:shield":26,"minecraft:cornflower":267,"minecraft:stone_stairs":14,"minecraft:iron_axe":1,"minecraft:wooden_sword":1,"minecraft:flint_and_steel":1,"minecraft:item_frame":9,"minecraft:compass":4,"minecraft:iron_shovel":7,"minecraft:cracked_stone_bricks":15,"minecraft:cartography_table":4,"minecraft:beef":52,"minecraft:oak_boat":80,"minecraft:spruce_slab":5,"minecraft:iron_nugget":80,"minecraft:poppy":221,"minecraft:light_gray_wool":22,"minecraft:minecart":1,"minecraft:chest":17,"minecraft:sugar_cane":680,"minecraft:birch_sapling":18,"minecraft:piston":1,"minecraft:phantom_membrane":9,"minecraft:egg":3068,"minecraft:dark_oak_sapling":40,"minecraft:sandstone":424,"minecraft:end_stone":46,"minecraft:stone":2271,"minecraft:bowl":4,"minecraft:spruce_fence":7,"minecraft:trident":2,"minecraft:carrot":552,"minecraft:redstone":186,"minecraft:prismarine_crystals":19,"minecraft:dark_oak_planks":5,"minecraft:tnt":5,"minecraft:diamond_chestplate":2,"minecraft:arrow":327,"minecraft:stone_shovel":4,"minecraft:cooked_cod":75,"minecraft:beetroot_seeds":2,"minecraft:jungle_stairs":1,"minecraft:peony":180,"minecraft:nether_bricks":48,"minecraft:shears":13,"minecraft:hay_block":52,"minecraft:pink_tulip":15,"minecraft:saddle":3,"minecraft:gold_ingot":17,"minecraft:mutton":24,"minecraft:white_wool":51,"minecraft:oxeye_daisy":152,"minecraft:lime_bed":2,"minecraft:clock":2,"minecraft:salmon":14,"minecraft:cut_sandstone":7,"minecraft:leather":30,"minecraft:fern":4,"minecraft:red_mushroom":1,"minecraft:birch_planks":26,"minecraft:filled_map":49,"minecraft:oak_log":253,"minecraft:lily_pad":318,"minecraft:yellow_bed":2,"minecraft:gunpowder":38,"minecraft:cobblestone_stairs":23,"minecraft:paper":402,"minecraft:white_banner":7,"minecraft:orange_terracotta":5,"minecraft:cooked_mutton":4,"minecraft:apple":7,"minecraft:stone_bricks":277,"minecraft:kelp":821,"minecraft:stone_pickaxe":8,"minecraft:rabbit_hide":1,"minecraft:heart_of_the_sea":2,"minecraft:oak_fence_gate":6,"minecraft:iron_ingot":368,"minecraft:cooked_chicken":347,"minecraft:iron_ore":136,"minecraft:iron_sword":42,"minecraft:dark_oak_stairs":2,"minecraft:book":26,"minecraft:oak_slab":6,"minecraft:emerald_block":2,"minecraft:sweet_berries":1458,"minecraft:birch_boat":5,"minecraft:pumpkin":2,"minecraft:quartz":171,"minecraft:dandelion":272,"minecraft:gravel":144,"minecraft:lava_bucket":1,"minecraft:spruce_sapling":40,"minecraft:white_bed":11,"minecraft:spruce_log":261,"minecraft:dragon_egg":2,"minecraft:spruce_door":1,"minecraft:spider_eye":33,"minecraft:diamond_shovel":3,"minecraft:coal_ore":6,"minecraft:slime_ball":3,"minecraft:stone_axe":1,"minecraft:iron_helmet":22,"minecraft:diamond_axe":1,"minecraft:mossy_cobblestone_stairs":8,"minecraft:terracotta":1,"minecraft:baked_potato":172,"minecraft:black_wool":4,"minecraft:pink_dye":1,"minecraft:coal":361,"minecraft:sunflower":66,"minecraft:ender_pearl":10}},"DataVersion":2584}